tokopedia_wrapper/__init__.py
tokopedia_wrapper/base.py
tokopedia_wrapper/product.py
tokopedia_wrapper/query.py
tokopedia_wrapper-0.4.dist-info/METADATA
tokopedia_wrapper-0.4.dist-info/WHEEL
tokopedia_wrapper-0.4.dist-info/top_level.txt
tokopedia_wrapper-0.4.dist-info/RECORD
