Metadata-Version: 2.1
Name: tokopedia-wrapper
Version: 0.4
Summary: Library that wrap tokopedia.com graphql api using requests
Author: Hariz Sufyan Munawar
Author-email: contact@munawariz.dev
License: Apache License
